README.md
setup.py
space_api/__init__.py
space_api/api.py
space_api/constants.py
space_api/livequery.py
space_api/realtime.py
space_api/response.py
space_api/service.py
space_api/transport.py
space_api/user_man.py
space_api/utils.py
space_api/mongo/__init__.py
space_api/mongo/aggregate.py
space_api/mongo/batch.py
space_api/mongo/delete.py
space_api/mongo/get.py
space_api/mongo/insert.py
space_api/mongo/mongo.py
space_api/mongo/update.py
space_api/proto/__init__.py
space_api/proto/codegen.py
space_api/proto/server_pb2.py
space_api/proto/server_pb2_grpc.py
space_api/sql/__init__.py
space_api/sql/batch.py
space_api/sql/delete.py
space_api/sql/get.py
space_api/sql/insert.py
space_api/sql/sql.py
space_api/sql/update.py
space_api_py.egg-info/PKG-INFO
space_api_py.egg-info/SOURCES.txt
space_api_py.egg-info/dependency_links.txt
space_api_py.egg-info/requires.txt
space_api_py.egg-info/top_level.txt