Metadata-Version: 2.1
Name: space-api-py
Version: 0.9.1
Summary: Space Cloud Client Python API
Home-page: https://github.com/spaceuptech/space-api-python
Author: Space Up Tech
Author-email: info@spaceuptech.com
License: Apache License, Version 2.0
Platform: UNKNOWN
Classifier: Intended Audience :: Developers
Classifier: License :: OSI Approved :: Apache Software License
Classifier: Programming Language :: Python :: 3
Classifier: Programming Language :: Python :: 3.7
